pytest_select/__init__.py
pytest_select/plugin.py
pytest_select-0.1.2.dist-info/entry_points.txt
pytest_select-0.1.2.dist-info/WHEEL
pytest_select-0.1.2.dist-info/METADATA
pytest_select-0.1.2.dist-info/RECORD
